server.py
salesforce_mcp-0.1.1.dist-info/licenses/LICENSE
salesforcemcp/definitions.py
salesforcemcp/implementations.py
salesforcemcp/sfdc_client.py
salesforcemcp/assets/field.tmpl
salesforcemcp/assets/field_permission.tmpl
salesforcemcp/assets/profile.tmpl
salesforcemcp/assets/create_custom_app_tmpl/package.xml
salesforcemcp/assets/create_custom_app_tmpl/applications/Template.app-meta.xml
salesforcemcp/assets/create_custom_metadata_type_tmpl/package.xml
salesforcemcp/assets/create_custom_metadata_type_tmpl/objects/##api_name##.object
salesforcemcp/assets/create_object_tmpl/package.xml
salesforcemcp/assets/create_object_tmpl/objects/##api_name##.object
salesforcemcp/assets/create_tab_tmpl/package.xml
salesforcemcp/assets/create_tab_tmpl/tabs/Template.tab-meta.xml
salesforcemcp/assets/delete_fields_tmpl/destructiveChanges.xml
salesforcemcp/assets/delete_fields_tmpl/package.xml
salesforce_mcp-0.1.1.dist-info/METADATA
salesforce_mcp-0.1.1.dist-info/WHEEL
salesforce_mcp-0.1.1.dist-info/entry_points.txt
salesforce_mcp-0.1.1.dist-info/top_level.txt
salesforce_mcp-0.1.1.dist-info/RECORD
