Metadata-Version: 2.4
Name: salesforce-mcp
Version: 0.1.1
Summary: Salesforce MCP Connector allows you to interact with your Salesforce data and metadata using natural language.
Author-email: Salesforce MCP <salesforce.mcp.2@gmail.com>
License: MIT License
Project-URL: Homepage, https://github.com/salesforce-mcp/salesforce-mcp
Project-URL: Bug Tracker, https://github.com/salesforce-mcp/salesforce-mcp/issues
Keywords: salesforce,mcp,api,automation,model-context-protocol
Classifier: Development Status :: 3 - Alpha
Classifier: Intended Audience :: Developers
Classifier: Intended Audience :: System Administrators
Classifier: License :: OSI Approved :: MIT License
Classifier: Programming Language :: Python :: 3
Classifier: Programming Language :: Python :: 3.10
Classifier: Programming Language :: Python :: 3.11
Classifier: Operating System :: OS Independent
Classifier: Topic :: Software Development :: Libraries :: Python Modules
Classifier: Topic :: Utilities
Requires-Python: >=3.10
License-File: LICENSE
Requires-Dist: mcp
Requires-Dist: simple-salesforce
Requires-Dist: python-dotenv
Dynamic: license-file
